s2cloudless/__init__.py
s2cloudless/cloud_detector.py
s2cloudless/pixel_classifier.py
s2cloudless/py.typed
s2cloudless/utils.py
s2cloudless/models/pixel_s2_cloud_detector_lightGBM_v0.1.txt
s2cloudless-1.7.1.dist-info/METADATA
s2cloudless-1.7.1.dist-info/WHEEL
s2cloudless-1.7.1.dist-info/licenses/LICENSE.md
s2cloudless-1.7.1.dist-info/RECORD
