Metadata-Version: 2.1
Name: s2cloudless
Version: 1.7.1
Summary: Sentinel Hub's cloud detector for Sentinel-2 imagery
Project-URL: Homepage, https://github.com/sentinel-hub/sentinel2-cloud-detector
Project-URL: Issues, https://github.com/sentinel-hub/sentinel2-cloud-detector/issues
Project-URL: Source, https://github.com/sentinel-hub/sentinel2-cloud-detector
Project-URL: Forum, https://forum.sentinel-hub.com
Author-email: Sinergise EO research team <eoresearch@sinergise.com>
License: ## creative commons
License-File: LICENSE.md
Classifier: Development Status :: 5 - Production/Stable
Classifier: Intended Audience :: Education
Classifier: Intended Audience :: Science/Research
Classifier: Operating System :: MacOS
Classifier: Operating System :: Microsoft :: Windows
Classifier: Operating System :: Unix
Classifier: Programming Language :: Python
Classifier: Programming Language :: Python :: 3
Classifier: Programming Language :: Python :: 3.8
Classifier: Programming Language :: Python :: 3.9
Classifier: Programming Language :: Python :: 3.10
Classifier: Programming Language :: Python :: 3.11
Classifier: Topic :: Scientific/Engineering
Requires-Python: >=3.8
Requires-Dist: lightgbm>=2.0.11
Requires-Dist: numpy>=1.13.3
Requires-Dist: opencv-python-headless
Requires-Dist: sentinelhub>=3.9.0
Requires-Dist: typing-extensions
Provides-Extra: dev
Requires-Dist: build; extra == 'dev'
Requires-Dist: mypy; extra == 'dev'
Requires-Dist: pre-commit; extra == 'dev'
Requires-Dist: pylint>=2.14.0; extra == 'dev'
Requires-Dist: pytest-cov; extra == 'dev'
Requires-Dist: pytest>=3.0.0; extra == 'dev'
Requires-Dist: twine; extra == 'dev'
